pulumi_aws_website/__init__.py
pulumi_aws_website/config.py
pulumi_aws_website/tests.py
pulumi_aws_website-0.1.3.data/data/requirements.txt
pulumi_aws_website-0.1.3.dist-info/LICENSE
pulumi_aws_website-0.1.3.dist-info/METADATA
pulumi_aws_website-0.1.3.dist-info/WHEEL
pulumi_aws_website-0.1.3.dist-info/top_level.txt
pulumi_aws_website-0.1.3.dist-info/RECORD
