Metadata-Version: 2.1
Name: pulumi-aws-website
Version: 0.1.3
Summary: Pulumi ComponentResource for create website based on CloudFront and S3
Home-page: https://github.com/jetbrains-infra/pulumi-aws-website
Author: Vadim Reyder
Author-email: vadim.reyder@gmail.com
License: MIT
Platform: UNKNOWN
License-File: LICENSE
Requires-Dist: pulumi (<4.0.0,>=3.0.0)
Requires-Dist: pulumi-aws (<5.0.0,>=4.0.0)
